{
  "project_info": {
    "project_number": "684908153382",
    "project_id": "wallet-dfbd2",
    "storage_bucket": "wallet-dfbd2.appspot.com"
  },
  "client": [
    {
      "client_info": {
        "mobilesdk_app_id": "1:684908153382:android:12df5520e5be159d8234e7",
        "android_client_info": {
          "package_name": "com.example.wallet"
        }
      },
      "oauth_client": [
        {
          "client_id": "684908153382-gjapb2tafruvj11kbaudl0bfi6o29f2b.apps.googleusercontent.com",
          "client_type": 3
        }
      ],
      "api_key": [
        {
          "current_key": "AIzaSyDFW5RJzE-sL8pUPpHjOoTPXWcbWPGNMSo"
        }
      ],
      "services": {
        "appinvite_service": {
          "other_platform_oauth_client": [
            {
              "client_id": "684908153382-gjapb2tafruvj11kbaudl0bfi6o29f2b.apps.googleusercontent.com",
              "client_type": 3
            }
          ]
        }
      }
    }
  ],
  "configuration_version": "1"
}